rich_tracebacks-2.0.0.dist-info/METADATA
rich_tracebacks-2.0.0.dist-info/WHEEL
rich_tracebacks-2.0.0.dist-info/entry_points.txt
rich_tracebacks-2.0.0.dist-info/licenses/LICENSE.md
rich_tracebacks.pth
rich_tracebacks/__init__.py
rich_tracebacks-2.0.0.dist-info/RECORD
