Metadata-Version: 2.4
Name: rich-tracebacks
Version: 2.0.0
Summary: Automatic installation of Rich's traceback handler
Author-Email: celsius narhwal <hello@celsiusnarhwal.dev>
License-Expression: MIT
Project-URL: Repository, https://github.com/celsiusnarhwal/rich-tracebacks
Project-URL: Issues, https://github.com/celsiusnarhwal/rich-tracebacks/issues
Requires-Python: >=3.6.2
Requires-Dist: rich>=12
